{
  "nummer" : 16,
  "titel" : "und der Zauberspiegel",
  "autor" : "M. V. Carey",
  "hörspielskriptautor" : "H. G. Francis",
  "beschreibung" : "Justus, Bob und Peter sind ja glücklicherweise schon allerlei gewohnt. Wenn also jemand erzählt, in einem riesigen, spanischen Spiegel, der Mrs. Darnley gehört, spuke es, und wenn dann nachts in Mrs. Darnleys Haus seltsame Geräusche zu hören sind, dann kriegt zumindest Justus weniger eine Gänsehaut, als vielmehr Lust, der Sache auf den Grund zu gehen. Kaum beginnen die drei ??? zu ermitteln, stoßen sie auch schon auf jede Menge Verdächtiges: Ein Spanier, der sich für den Spiegel interessiert, wird zusammengeschlagen, der Präsident des Staates Ruffino weiß Geheimnisvolles vom Spiegel und warnt vor einem gewissen Juan Gomez, politische lntrigen scheinen sich am Spiegel zu entzünden, – schließlich wird sogar ein Junge entführt! Und das alles wegen eines alten Spiegels? Sehr merkwürdig! Doch unsere drei cleveren Detektive werden die Wahrheit herausfinden – wetten?",
  "veröffentlichungsdatum" : "1980-10-01",
  "kapitel" : [
    {
      "titel" : "Haltet den Dieb!",
      "start" : 0,
      "end" : 387133
    },
    {
      "titel" : "Chiavos Fluch",
      "start" : 387133,
      "end" : 639960
    },
    {
      "titel" : "Justus wittert ein Geheimnis",
      "start" : 639960,
      "end" : 916000
    },
    {
      "titel" : "Spuk im Spiegel",
      "start" : 916000,
      "end" : 1268573
    },
    {
      "titel" : "Ein rätselhafter Brief",
      "start" : 1268573,
      "end" : 1570680
    },
    {
      "titel" : "Verräterisches Glockenspiel",
      "start" : 1570680,
      "end" : 1927947
    },
    {
      "titel" : "Wettlauf gegen die Uhr",
      "start" : 1927947,
      "end" : 2204560
    },
    {
      "titel" : "Der Spiegel gibt sein Geheimnis preis",
      "start" : 2204560,
      "end" : 2551347
    }
  ],
  "sprecher" : [
    [
      "Hitchcock, Erzähler",
      "Peter Pasetti"
    ],
    [
      "Justus Jonas, Erster Detektiv",
      "Oliver Rohrbeck"
    ],
    [
      "Peter Shaw, Zweiter Detektiv",
      "Jens Wawrczeck"
    ],
    [
      "Bob Andrews, Recherchen und Archiv",
      "Andreas Fröhlich"
    ],
    [
      "Mrs. Darnley",
      "Gisela Trowe"
    ],
    [
      "Jeff Darnley",
      "Mike Henning"
    ],
    [
      "Jenny Darnley",
      "Marlen Krause"
    ],
    [
      "Senior Santora",
      "Jürgen Thormann"
    ],
    [
      "Morton",
      "Andreas von der Meden"
    ],
    [
      "Onkel Titus",
      "Hans Meinhardt"
    ],
    [
      "Gomez",
      "Karl-Heinz Gerdesmann"
    ],
    [
      "Brotverkäufer",
      "Harald Pages"
    ]
  ],
  "links" : {
    "json" : "http://dreimetadaten.de/data/Serie/016/metadata.json",
    "cover_itunes" : "http://is5.mzstatic.com/image/thumb/Music22/v4/1d/6e/77/1d6e77a2-74de-ec6f-f1a7-00e72c4c5587/source/3000x0w.png"
  }
}
