{
  "nummer" : 95,
  "titel" : "Geheime Zeichen",
  "autor" : "Boris Pfeiffer",
  "hörspielskriptautor" : "Ulf Blanck",
  "kurzbeschreibung" : "Einbruch in einer Villa!",
  "beschreibung" : "Bei der Untersuchung des Tatorts fällt den drei ??? Kids ein merkwürdiges Kreidezeichen auf. Was hat es damit auf sich? Justus, Peter und Bob müssen Kommissar Reynolds helfen, weitere Einbrüche zu verhindern.",
  "veröffentlichungsdatum" : "2024-03-08",
  "sprechrollen" : [
    {
      "rolle" : "Erzähler",
      "sprecher" : "Johannes Steck"
    },
    {
      "rolle" : "Justus Jonas, Erster Detektiv",
      "sprecher" : "Jannik Schümann"
    },
    {
      "rolle" : "Peter Shaw, Zweiter Detektiv",
      "sprecher" : "Yoshij Grimm"
    },
    {
      "rolle" : "Bob Andrews, Recherchen und Archiv",
      "sprecher" : "David Wittmann"
    },
    {
      "rolle" : "Kommissar Reynolds",
      "sprecher" : "Bert Franzke"
    },
    {
      "rolle" : "Tante Mathilda",
      "sprecher" : "Ingrid Capelle"
    },
    {
      "rolle" : "Mr. Shaw",
      "sprecher" : "Oliver Schmitz"
    },
    {
      "rolle" : "Jamie",
      "sprecher" : "Thomas Fedrowitz"
    },
    {
      "rolle" : "Jacqueline",
      "sprecher" : "Uta Dänekamp"
    },
    {
      "rolle" : "Spähvogel",
      "sprecher" : "David M. Schulze"
    },
    {
      "rolle" : "Mrs. Clifford",
      "sprecher" : "Ulrike Hübschmann"
    },
    {
      "rolle" : "Kralle",
      "sprecher" : "Elmar Gutmann"
    },
    {
      "rolle" : "Nachteule",
      "sprecher" : "Simon Köslich"
    },
    {
      "rolle" : "Sergeant Bofinger",
      "sprecher" : "Michael Lott"
    }
  ],
  "links" : {
    "json" : "http://dreimetadaten.de/data/Kids/095/metadata.json",
    "cover_itunes" : "http://a1.mzstatic.com/r40/Music211/v4/f8/1e/09/f81e09a8-9de6-ec9d-60d5-ac9675236f15/196872226485.jpg",
    "dreifragezeichen" : "https://www.dreifragezeichen-kids.de/produktwelt/produkt-details/geheime-zeichen",
    "appleMusic" : "https://music.apple.com/de/album/1752882887"
  },
  "unvollständig" : true
}
