{
  "teile" : [
    {
      "teilNummer" : 5,
      "titel" : "SOS",
      "autor" : "Marco Sonnleitner",
      "beschreibung" : "Als die drei ??? vom Strand kommen und auf dem Weg nach Hause sind, sehen sie ein SOS-Signal, das aus einem Haus gesendet wird. Eigentlich steht das Haus leer …",
      "veröffentlichungsdatum" : "2011-12-10",
      "sprecher" : [
        [
          "Erzähler",
          "Thomas Fritsch"
        ],
        [
          "Justus Jonas",
          "Oliver Rohrbeck"
        ],
        [
          "Peter Shaw",
          "Jens Wawrczeck"
        ],
        [
          "Bob Andrews",
          "Andreas Fröhlich"
        ],
        [
          "Marty",
          "Philipp Draeger"
        ],
        [
          "Fred",
          "Guido Bernadotte"
        ],
        [
          "1. Mann",
          "Rasmus Rakete"
        ],
        [
          "2. Mann",
          "Patrick Perales"
        ]
      ],
      "links" : {
        "json" : "http://dreimetadaten.de/data/Kurzgeschichten/und-die-Geisterlampe/2/5/metadata.json",
        "ffmetadata" : "http://dreimetadaten.de/data/Kurzgeschichten/und-die-Geisterlampe/2/5/ffmetadata.txt"
      }
    },
    {
      "teilNummer" : 6,
      "titel" : "Der graue Dämon",
      "autor" : "Hendrik Buchna",
      "beschreibung" : "Auf dem Weg nach Hause wird Peter plötzlich von einem unheimlichen, grauen Dämon verfolgt. Ihm bleibt nur noch ein Ausweg: Die Flucht …",
      "veröffentlichungsdatum" : "2011-12-12",
      "sprecher" : [
        [
          "Peter Shaw",
          "Jens Wawrczeck"
        ]
      ],
      "links" : {
        "json" : "http://dreimetadaten.de/data/Kurzgeschichten/und-die-Geisterlampe/2/6/metadata.json",
        "ffmetadata" : "http://dreimetadaten.de/data/Kurzgeschichten/und-die-Geisterlampe/2/6/ffmetadata.txt"
      }
    },
    {
      "teilNummer" : 7,
      "titel" : "Das Lehrstück",
      "autor" : "Kari Erlhoff",
      "beschreibung" : "Peters ehemalige Klavierlehrerin, Mrs. Floyd, engagiert die drei ???, um herauszufinden, wo ihre verstorbene Mutter ihr Erbe versteckt haben könnte …",
      "veröffentlichungsdatum" : "2011-12-14",
      "sprecher" : [
        [
          "Erzähler",
          "Thomas Fritsch"
        ],
        [
          "Justus Jonas",
          "Oliver Rohrbeck"
        ],
        [
          "Peter Shaw",
          "Jens Wawrczeck"
        ],
        [
          "Bob Andrews",
          "Andreas Fröhlich"
        ],
        [
          "Mrs. Floyd",
          "Gabriele Libbach"
        ]
      ],
      "links" : {
        "json" : "http://dreimetadaten.de/data/Kurzgeschichten/und-die-Geisterlampe/2/7/metadata.json",
        "ffmetadata" : "http://dreimetadaten.de/data/Kurzgeschichten/und-die-Geisterlampe/2/7/ffmetadata.txt"
      }
    },
    {
      "teilNummer" : 8,
      "titel" : "Das Rätsel der schwarzen Nadel",
      "autor" : "Hendrik Buchna",
      "beschreibung" : "Die drei ??? erhalten den Auftrag, bei der Übergabe einer schwarzen Nadel dabei zu sein. Aber geht es dabei wirklich nur um das Schmuckstück?",
      "veröffentlichungsdatum" : "2011-12-16",
      "sprecher" : [
        [
          "Erzähler",
          "Thomas Fritsch"
        ],
        [
          "Justus Jonas",
          "Oliver Rohrbeck"
        ],
        [
          "Peter Shaw",
          "Jens Wawrczeck"
        ],
        [
          "Bob Andrews",
          "Andreas Fröhlich"
        ],
        [
          "Tante Mathilda Jonas",
          "Karin Lieneweg"
        ],
        [
          "Vincent Grimes",
          "Konstantin Graudus"
        ]
      ],
      "links" : {
        "json" : "http://dreimetadaten.de/data/Kurzgeschichten/und-die-Geisterlampe/2/8/metadata.json",
        "ffmetadata" : "http://dreimetadaten.de/data/Kurzgeschichten/und-die-Geisterlampe/2/8/ffmetadata.txt"
      }
    }
  ],
  "teilNummer" : 2,
  "buchstabe" : "B",
  "kapitel" : [
    {
      "titel" : "SOS",
      "start" : 0,
      "end" : 661640
    },
    {
      "titel" : "Der graue Dämon",
      "start" : 661640,
      "end" : 1217947
    },
    {
      "titel" : "Das Lehrstück",
      "start" : 1217947,
      "end" : 1967360
    },
    {
      "titel" : "Das Rätsel der schwarzen Nadel",
      "start" : 1967360,
      "end" : 2679040
    }
  ],
  "links" : {
    "json" : "http://dreimetadaten.de/data/Kurzgeschichten/und-die-Geisterlampe/2/metadata.json",
    "xld_log" : "http://dreimetadaten.de/data/Kurzgeschichten/und-die-Geisterlampe/2/rip_log.txt"
  }
}
