{
  "nummer" : 106,
  "titel" : "Der Mann ohne Kopf",
  "autor" : "André Minninger",
  "hörspielskriptautor" : "André Minninger",
  "beschreibung" : "\"DJ-Devil\", von der Presse auch reißerisch \"Satans-DJ\" genannt, scheint wahrlich über teuflische Fähigkeiten zu verfügen. Der geheimnisvolle Discjockey ohne Kopf entlockt am Wochenende seinem Mischpult die unheimlichsten Beats, die die tanzenden Besucher in rasende Euphorie versetzen. Doch plötzlich gerät die Szenerie außer Kontrolle. Die drei ??? sind an diesem Abend zufällige Besucher in der Diskothek \"Planet-Evil\" und werden Zeugen eines unheimlichen Phänomens, das Justus an die Grenzen seiner Logik katapultiert …",
  "veröffentlichungsdatum" : "2002-09-16",
  "kapitel" : [
    {
      "titel" : "Saturday Night Fever",
      "start" : 0,
      "end" : 568547
    },
    {
      "titel" : "Disco-Inferno",
      "start" : 568547,
      "end" : 1206787
    },
    {
      "titel" : "Mit dem Teufel im Bunde",
      "start" : 1206787,
      "end" : 1534827
    },
    {
      "titel" : "\"Devil-Dancer\"",
      "start" : 1534827,
      "end" : 2129680
    },
    {
      "titel" : "Die Kutte des Satans",
      "start" : 2129680,
      "end" : 2486853
    },
    {
      "titel" : "Massensuggestion",
      "start" : 2486853,
      "end" : 2950027
    },
    {
      "titel" : "Die letzte Ruhestätte",
      "start" : 2950027,
      "end" : 3828987
    },
    {
      "titel" : "Tödliches Abgas",
      "start" : 3828987,
      "end" : 4255213
    }
  ],
  "sprecher" : [
    [
      "Erzähler",
      "Thomas Fritsch"
    ],
    [
      "Justus Jonas, Erster Detektiv",
      "Oliver Rohrbeck"
    ],
    [
      "Peter Shaw, Zweiter Detektiv",
      "Jens Wawrczeck"
    ],
    [
      "Bob Andrews, Recherchen und Archiv",
      "Andreas Fröhlich"
    ],
    [
      "Amy Scream",
      "Marianne Kehlau"
    ],
    [
      "Monique Carrera",
      "Amanda Lear"
    ],
    [
      "Inspektor Cotta",
      "Holger Mahlich"
    ],
    [
      "Ellen",
      "Celine Fontanges"
    ],
    [
      "Pam",
      "Enie van de Meiklokjes"
    ],
    [
      "Jim Cowley",
      "Cäsar"
    ],
    [
      "Jeffrey",
      "Kim Alexander Frank"
    ],
    [
      "Mandy Robin",
      "Manuela Dahm"
    ],
    [
      "1. Sanitäter",
      "Robert Missler"
    ],
    [
      "2. Sanitäter",
      "Hartmut Kollakowsky"
    ],
    [
      "Bardame",
      "Monique Carrera [Amanda Lear]"
    ],
    [
      "Tante Mathilda",
      "Karin Lieneweg"
    ],
    [
      "Diskothekenbesucher",
      "Echt"
    ]
  ],
  "links" : {
    "json" : "http://dreimetadaten.de/data/Serie/106/metadata.json",
    "ffmetadata" : "http://dreimetadaten.de/data/Serie/106/ffmetadata.txt",
    "xld_log" : "http://dreimetadaten.de/data/Serie/106/rip_log.txt",
    "cover" : "http://dreimetadaten.de/data/Serie/106/cover.png",
    "cover_itunes" : "https://is1-ssl.mzstatic.com/image/thumb/Music60/v4/b8/49/6e/b8496eb3-a7be-e67a-7baa-f731978d5b97/886445751970.jpg/3000x0w.png",
    "cover_kosmos" : "https://s3.eu-central-1.amazonaws.com/kosmos.de/media/image/80/69/0f/0743219432520.jpg"
  }
}